pymulticopter/__init__.py
pymulticopter/base.py
pymulticopter/control.py
pymulticopter/estimator.py
pymulticopter/model.py
pymulticopter/test_bs_control.py
pymulticopter/test_fixed_time_estimator.py
pymulticopter/test_flvel.py
pymulticopter/test_oaf_att_control.py
pymulticopter/test_oaf_control.py
pymulticopter/test_quaternion_pos.py
pymulticopter/test_sm_att_control.py
pymulticopter-0.0.1.dist-info/METADATA
pymulticopter-0.0.1.dist-info/WHEEL
pymulticopter-0.0.1.dist-info/top_level.txt
pymulticopter-0.0.1.dist-info/RECORD
