Metadata-Version: 2.1
Name: pymulticopter
Version: 0.0.1
Summary: A framework for performing numerical simulation of multicopter system
Home-page: https://github.com/minii93/pysimenv-multicopter
Author: Sangmin Lee
Author-email: everlastingminii@gmail.com
Classifier: Programming Language :: Python :: 3
Classifier: License :: OSI Approved :: MIT License
Classifier: Operating System :: OS Independent
Requires-Python: >=3.6
Requires-Dist: pysimenv
Requires-Dist: numpy
Requires-Dist: scipy
Requires-Dist: matplotlib
Requires-Dist: h5py
Requires-Dist: pytictoc
Requires-Dist: pyquaternion
